pycreep/__init__.py
pycreep/allowables.py
pycreep/data.py
pycreep/dataset.py
pycreep/fatigue.py
pycreep/gpr.py
pycreep/methods.py
pycreep/omega.py
pycreep/reports.py
pycreep/time_independent.py
pycreep/ttp.py
pycreep/units.py
pycreep/wilshire.py
pycreep-1.2.0.dist-info/licenses/LICENSE
pycreep-1.2.0.dist-info/METADATA
pycreep-1.2.0.dist-info/WHEEL
pycreep-1.2.0.dist-info/top_level.txt
pycreep-1.2.0.dist-info/RECORD
