Metadata-Version: 2.4
Name: pycreep
Version: 1.2.0
Summary: Python package for correlating and extrapoling time dependent creep data
Author-email: Mark Messner <messner@anl.gov>
License: Copyright 2022, UChicago Argonne, LLC
Project-URL: Homepage, https://github.com/applied-material-modeling/pycreep
Project-URL: Issues, https://github.com/applied-material-modeling/pycreep/issues
Classifier: Programming Language :: Python :: 3
Classifier: License :: OSI Approved :: MIT License
Classifier: Operating System :: OS Independent
Requires-Python: >=3.8
License-File: LICENSE
Requires-Dist: pint
Requires-Dist: numpy
Requires-Dist: scipy
Requires-Dist: pandas
Requires-Dist: openpyxl
Requires-Dist: torch
Requires-Dist: pyro-ppl
Requires-Dist: torchquad
Dynamic: license-file
